manim_nerdfont_icons/docbuild/__init__.py
manim_nerdfont_icons/docbuild/_create_icon_table_for_docs.py
manim_nerdfont_icons/docbuild/_csv_table_export.py
manim_nerdfont_icons/docbuild/manta_directive.py
manim_nerdfont_icons/icons.py
manim_nerdfont_icons/icons_dict.py
manim_nerdfont_icons/resources/SymbolsNerdFontMono-Regular.ttf
manim_nerdfont_icons/resources/__init__.py
manim_nerdfont_icons-1.0.2.dist-info/LICENSE
manim_nerdfont_icons-1.0.2.dist-info/METADATA
manim_nerdfont_icons-1.0.2.dist-info/WHEEL
manim_nerdfont_icons-1.0.2.dist-info/RECORD
